getconf/__init__.py
getconf/base.py
getconf/finders.py
getconf-1.11.1.dist-info/LICENSE
getconf-1.11.1.dist-info/METADATA
getconf-1.11.1.dist-info/WHEEL
getconf-1.11.1.dist-info/top_level.txt
getconf-1.11.1.dist-info/RECORD
