Metadata-Version: 2.1
Name: getconf
Version: 1.11.1
Summary: getconf, a versatile configuration lib for Python projects
Home-page: https://github.com/Polyconseil/getconf/
Author: Polyconseil
Author-email: opensource+getconf@polyconseil.fr
License: BSD
Download-URL: https://pypi.python.org/pypi/getconf/
Keywords: configuration,environment,setup,getconf,config
Platform: OS Independent
Classifier: Development Status :: 5 - Production/Stable
Classifier: Intended Audience :: Developers
Classifier: License :: OSI Approved :: BSD License
Classifier: Operating System :: OS Independent
Classifier: Programming Language :: Python
Classifier: Programming Language :: Python :: 3
Classifier: Programming Language :: Python :: 3.5
Classifier: Programming Language :: Python :: 3.6
Classifier: Programming Language :: Python :: 3.7
Classifier: Programming Language :: Python :: 3.8
Classifier: Programming Language :: Python :: 3.9
Classifier: Programming Language :: Python :: 3.10
Classifier: Topic :: Software Development
Classifier: Topic :: System :: Installation/Setup
Classifier: Topic :: System :: Systems Administration
Requires-Python: >=2.7,!=3.0.*,!=3.1.*,!=3.2.*
License-File: LICENSE
